EasyDraw/Canvas.py
EasyDraw/Color.py
EasyDraw/Tools.py
EasyDraw/Vector.py
EasyDraw/__init__.py
EasyDraw-0.6.3.dist-info/LICENSE
EasyDraw-0.6.3.dist-info/METADATA
EasyDraw-0.6.3.dist-info/WHEEL
EasyDraw-0.6.3.dist-info/top_level.txt
EasyDraw-0.6.3.dist-info/RECORD
